{
  "type": "CustomCode_geocoding-ban",
  "inputs": {
    "input": {
      "items": [
        {
          "ref": "accidents_caracteristiques_prep3",
          "deps": []
        }
      ]
    }
  },
  "outputs": {
    "output": {
      "items": [
        {
          "ref": "accidents_caracteristiques_geocoded_citycode",
          "appendMode": false
        }
      ]
    }
  },
  "neverRecomputeExistingPartitions": false,
  "optionalDependencies": false,
  "params": {
    "customConfig": {
      "server_address": "http://datalab-ban",
      "concurent_requests": 1.0,
      "prefix": "ban_",
      "columns": [
        "adr"
      ],
      "city_code": "current_city_code",
      "error_col": "",
      "timeout": 1000.0,
      "lines_per_request": 10.0
    }
  },
  "checklists": {
    "checklists": []
  },
  "tags": [],
  "versionTag": {
    "versionNumber": 22,
    "lastModifiedBy": {
      "login": "grabenertr",
      "displayName": "Tristam Gräbener",
      "email": "tristam.grabener@interieur.gouv.fr"
    },
    "lastModifiedOn": 1488189062880
  },
  "customMeta": {
    "kv": {}
  },
  "redispatchPartitioning": false
}