{
  "type": "shaker",
  "inputs": {
    "main": {
      "items": [
        {
          "ref": "geocodage_quali_BAN",
          "deps": []
        }
      ]
    }
  },
  "outputs": {
    "main": {
      "items": [
        {
          "ref": "geocodage_quali_BAN_prepared",
          "appendMode": false
        }
      ]
    }
  },
  "neverRecomputeExistingPartitions": false,
  "optionalDependencies": false,
  "params": {
    "engine": "DSS_STREAM",
    "hadoopConfigKeys": []
  },
  "checklists": {
    "checklists": []
  },
  "tags": [],
  "versionTag": {
    "versionNumber": 3,
    "lastModifiedBy": {
      "login": "grabenertr",
      "displayName": "Tristam Gräbener",
      "email": "tristam.grabener@interieur.gouv.fr"
    },
    "lastModifiedOn": 1483631845467
  },
  "customMeta": {
    "kv": {}
  },
  "redispatchPartitioning": false
}