{
  "content": {
    "dataView": {
      "chartsEngine": "LINO",
      "sampling": {
        "selection": {
          "samplingMethod": "HEAD_SEQUENTIAL",
          "partitionSelectionMethod": "ALL",
          "maxRecords": 10000,
          "targetRatio": 0.02
        },
        "autoRefreshSample": false,
        "_refreshTrigger": 0
      },
      "steps": []
    },
    "dataset": "geocoded_by_concat_prepared",
    "chart": {
      "type": "scatter",
      "variant": "normal",
      "name": "Avg. of result_score by distance_ban_gps",
      "userEditedName": false,
      "genericDimension0": [],
      "genericDimension1": [],
      "genericMeasures": [],
      "xDimension": [],
      "yDimension": [],
      "uaXDimension": [
        {
          "column": "distance_ban_gps",
          "type": "NUMERICAL",
          "treatAsAlphanum": false,
          "sortBy": "NATURAL",
          "sortAscending": false,
          "isA": "ua"
        }
      ],
      "uaYDimension": [
        {
          "column": "result_score",
          "type": "NUMERICAL",
          "treatAsAlphanum": false,
          "sortBy": "NATURAL",
          "sortAscending": false,
          "isA": "ua"
        }
      ],
      "uaSize": [],
      "uaShape": [],
      "uaColor": [],
      "uaTooltip": [],
      "groupDimension": [],
      "xMeasure": [],
      "yMeasure": [],
      "colorMeasure": [],
      "sizeMeasure": [],
      "geometry": [],
      "tooltipMeasures": [],
      "boxplotBreakdownDim": [],
      "boxplotValue": [],
      "filters": [
        {
          "filterType": "ALPHANUM_FACET",
          "column": "result_type",
          "columnType": "ALPHANUM",
          "isA": "filter",
          "excludedValues": {
            "street": true,
            "___dku_no_value___": true,
            "housenumber": true,
            "locality": true,
            "city": true,
            "town": true,
            "village": true
          },
          "explicitExclude": false
        }
      ],
      "axis1LogScale": false,
      "axis2LogScale": false,
      "includeZero": true,
      "hexbinRadius": 20,
      "smoothing": false,
      "showLegend": true,
      "showXAxis": false,
      "strokeWidth": 1,
      "colorOptions": {
        "singleColor": "#659a88",
        "transparency": 0.75,
        "colorPalette": "default",
        "ccScaleMode": "NORMAL"
      },
      "colorPaletteType": "LINEAR",
      "bubblesOptions": {
        "defaultRadius": 5.0
      },
      "computeMode": "NORMAL",
      "xAxisMode": "NORMAL",
      "yAxisMode": "NORMAL",
      "pieOptions": {
        "donutHoleSize": 50.0
      },
      "scatterOptions": {
        "equalScales": false,
        "identityLine": false
      },
      "mapOptions": {
        "tilesLayer": "cartodb-positron",
        "lockSquareGrid": false
      },
      "mapGridOptions": {
        "gridLonDeg": 0.6,
        "gridLatDeg": 0.6
      },
      "thumbnailData": "data:image/png;base64,iVBORw0KGgoAAAANSUhEUgAAADwAAAAoCAYAAACiu5n/AAAAIElEQVRoge3BMQEAAADCoPVPbQo/oAAAAAAAAAAAAHgaJagAAXCxjHYAAAAASUVORK5CYII\u003d",
      "disableSafetyLimits": false,
      "useLiveProcessingIfAvailable": true
    }
  },
  "name": "Avg. of result_score by distance_ban_gps",
  "type": "CHART",
  "miniature": {
    "type": "chart",
    "showTitle": true,
    "fullImage": true
  },
  "fullView": {
    "descriptionPosition": "right"
  },
  "description": "",
  "tags": [],
  "checklists": {
    "checklists": []
  },
  "createdBy": "grabenertr",
  "createdOn": 1484835424893
}