{
  "type": "ElasticSearch",
  "params": {
    "connection": "el",
    "index": "es2_2005_2015_accidents_caracteristiques_lieux",
    "type": "es2_2005_2015_accidents_caracteristiques_lieux",
    "rawCopyColumns": "*",
    "frameSize": 10000,
    "partitioned": false
  },
  "checks": [],
  "managed": true,
  "schema": {
    "userModified": false,
    "columns": [
      {
        "name": "Num_Acc",
        "type": "string",
        "timestampNoTzAsDate": false,
        "maxLength": -1
      },
      {
        "name": "mois",
        "type": "bigint",
        "timestampNoTzAsDate": false,
        "maxLength": -1
      },
      {
        "name": "lum",
        "type": "string",
        "timestampNoTzAsDate": false,
        "maxLength": 16200
      },
      {
        "name": "agg",
        "type": "string",
        "timestampNoTzAsDate": false,
        "maxLength": 16200
      },
      {
        "name": "int",
        "type": "string",
        "timestampNoTzAsDate": false,
        "maxLength": 16200
      },
      {
        "name": "atm",
        "type": "string",
        "timestampNoTzAsDate": false,
        "maxLength": 16200
      },
      {
        "name": "col",
        "type": "string",
        "timestampNoTzAsDate": false,
        "maxLength": 16200
      },
      {
        "name": "adr",
        "type": "string",
        "timestampNoTzAsDate": false,
        "maxLength": 16200
      },
      {
        "name": "dep",
        "type": "string",
        "timestampNoTzAsDate": false,
        "maxLength": 16200
      },
      {
        "name": "date",
        "type": "date",
        "timestampNoTzAsDate": false,
        "maxLength": -1
      },
      {
        "name": "ANNEE",
        "type": "bigint",
        "timestampNoTzAsDate": false,
        "maxLength": -1
      },
      {
        "name": "SEMAINE",
        "type": "bigint",
        "timestampNoTzAsDate": false,
        "maxLength": -1
      },
      {
        "name": "LIBELLE_JOUR",
        "type": "string",
        "timestampNoTzAsDate": false,
        "maxLength": 16200
      },
      {
        "name": "HEURE",
        "type": "bigint",
        "timestampNoTzAsDate": false,
        "maxLength": -1
      },
      {
        "name": "original_city_code",
        "type": "bigint",
        "timestampNoTzAsDate": false,
        "maxLength": -1
      },
      {
        "name": "original_name",
        "type": "string",
        "timestampNoTzAsDate": false,
        "maxLength": 16200
      },
      {
        "name": "current_city_code",
        "type": "bigint",
        "timestampNoTzAsDate": false,
        "maxLength": -1
      },
      {
        "name": "current_name",
        "type": "string",
        "timestampNoTzAsDate": false,
        "maxLength": 16200
      },
      {
        "name": "latitude",
        "type": "double",
        "timestampNoTzAsDate": false,
        "maxLength": -1
      },
      {
        "name": "geo_type",
        "type": "string",
        "timestampNoTzAsDate": false,
        "maxLength": 16200
      },
      {
        "name": "longitude",
        "type": "double",
        "timestampNoTzAsDate": false,
        "maxLength": -1
      },
      {
        "name": "geo_source",
        "type": "string",
        "timestampNoTzAsDate": false,
        "maxLength": 16200
      },
      {
        "name": "geo_score",
        "type": "double",
        "timestampNoTzAsDate": false,
        "maxLength": -1
      },
      {
        "name": "geopoint",
        "type": "string",
        "timestampNoTzAsDate": false,
        "maxLength": 16200
      },
      {
        "name": "NOM_DEPT",
        "type": "string",
        "timestampNoTzAsDate": false,
        "maxLength": 16200
      },
      {
        "name": "NOM_REG",
        "type": "string",
        "timestampNoTzAsDate": false,
        "maxLength": 16200
      },
      {
        "name": "catr",
        "type": "string",
        "timestampNoTzAsDate": false,
        "maxLength": 16200
      },
      {
        "name": "voie",
        "type": "string",
        "timestampNoTzAsDate": false,
        "maxLength": 16200
      },
      {
        "name": "v1",
        "type": "string",
        "timestampNoTzAsDate": false,
        "maxLength": 16200
      },
      {
        "name": "v2",
        "type": "string",
        "timestampNoTzAsDate": false,
        "maxLength": 16200
      },
      {
        "name": "circ",
        "type": "string",
        "timestampNoTzAsDate": false,
        "maxLength": 16200
      },
      {
        "name": "nbv",
        "type": "string",
        "timestampNoTzAsDate": false,
        "maxLength": 16200
      },
      {
        "name": "pr",
        "type": "string",
        "timestampNoTzAsDate": false,
        "maxLength": 16200
      },
      {
        "name": "pr1",
        "type": "string",
        "timestampNoTzAsDate": false,
        "maxLength": 16200
      },
      {
        "name": "vosp",
        "type": "string",
        "timestampNoTzAsDate": false,
        "maxLength": 16200
      },
      {
        "name": "prof",
        "type": "string",
        "timestampNoTzAsDate": false,
        "maxLength": 16200
      },
      {
        "name": "plan",
        "type": "string",
        "timestampNoTzAsDate": false,
        "maxLength": 16200
      },
      {
        "name": "lartpc",
        "type": "string",
        "timestampNoTzAsDate": false,
        "maxLength": 16200
      },
      {
        "name": "larrout",
        "type": "string",
        "timestampNoTzAsDate": false,
        "maxLength": 16200
      },
      {
        "name": "surf",
        "type": "string",
        "timestampNoTzAsDate": false,
        "maxLength": 16200
      },
      {
        "name": "infra",
        "type": "string",
        "timestampNoTzAsDate": false,
        "maxLength": 16200
      },
      {
        "name": "situ",
        "type": "string",
        "timestampNoTzAsDate": false,
        "maxLength": 16200
      },
      {
        "name": "env1",
        "type": "string",
        "timestampNoTzAsDate": false,
        "maxLength": 16200
      }
    ]
  },
  "partitioning": {
    "ignoreNonMatchingFile": false,
    "dimensions": []
  },
  "tags": [
    "creator_chabouisfr"
  ],
  "checklists": {
    "checklists": []
  },
  "flowOptions": {
    "rebuildBehavior": "NORMAL",
    "crossProjectBuildBehavior": "DEFAULT"
  },
  "versionTag": {
    "versionNumber": 5,
    "lastModifiedBy": {
      "login": "grabenertr",
      "displayName": "Tristam Gräbener",
      "email": "tristam.grabener@interieur.gouv.fr"
    },
    "lastModifiedOn": 1488276644791
  },
  "customMeta": {
    "kv": {}
  },
  "metrics": {
    "probes": [
      {
        "type": "basic",
        "enabled": true,
        "computeOnBuildMode": "PARTITION",
        "meta": {
          "name": "Basic data",
          "level": 0
        },
        "configuration": {}
      },
      {
        "type": "records",
        "enabled": true,
        "computeOnBuildMode": "NO",
        "meta": {
          "name": "Record count",
          "level": 0
        },
        "configuration": {}
      }
    ],
    "engineConfig": {
      "padRunsWithMetrics": false,
      "hive": {
        "active": true,
        "extraConf": [],
        "addDkuUdf": false
      },
      "basic": {},
      "dss": {
        "active": true,
        "selection": {
          "samplingMethod": "FULL",
          "partitionSelectionMethod": "ALL",
          "maxRecords": 10000,
          "targetRatio": 0.02
        }
      },
      "sql": {
        "active": true
      },
      "impala": {
        "active": true
      },
      "python": {}
    },
    "displayedState": {
      "metrics": [
        "basic:COUNT_COLUMNS",
        "records:COUNT_RECORDS"
      ]
    }
  },
  "metricsChecks": {
    "runOnBuild": false,
    "checks": [],
    "displayedState": {
      "checks": []
    }
  }
}